area_calculator_planefigures/__init__.py
area_calculator_planefigures/area_formulas.py
area_calculator_planefigures-0.0.1.dist-info/METADATA
area_calculator_planefigures-0.0.1.dist-info/WHEEL
area_calculator_planefigures-0.0.1.dist-info/top_level.txt
area_calculator_planefigures-0.0.1.dist-info/RECORD
