Metadata-Version: 2.1
Name: area_calculator_planefigures
Version: 0.0.1
Summary: Area Calculator Package for flat figures
Home-page: https://github.com/NathanniPadua/dio_desafio_criando_o_meu_primeiro_pacote_Python.git
Author: Nathanni
Author-email: nathannivpadua@gmail.com
License: UNKNOWN
Platform: UNKNOWN
Requires-Python: >=3.8
